colormycells/__init__.py
colormycells/colormap.py
colormycells-0.1.3.dist-info/licenses/LICENSE
colormycells-0.1.3.dist-info/METADATA
colormycells-0.1.3.dist-info/WHEEL
colormycells-0.1.3.dist-info/top_level.txt
colormycells-0.1.3.dist-info/RECORD
