Metadata-Version: 2.4
Name: colormycells
Version: 0.1.3
Summary: A Python package for creating perceptually uniform colormaps based on biological cell type similarity
Author-email: Your Name <your.email@example.com>
License: GPL-3.0
Project-URL: Homepage, https://github.com/yourusername/colormycells
Project-URL: Bug Reports, https://github.com/yourusername/colormycells/issues
Project-URL: Source, https://github.com/yourusername/colormycells
Project-URL: Documentation, https://github.com/yourusername/colormycells#readme
Keywords: bioinformatics,visualization,single-cell,colormap,perceptual
Classifier: Development Status :: 3 - Alpha
Classifier: Intended Audience :: Science/Research
Classifier: Topic :: Scientific/Engineering :: Bio-Informatics
Classifier: Topic :: Scientific/Engineering :: Visualization
Classifier: License :: OSI Approved :: GNU General Public License v3 (GPLv3)
Classifier: Programming Language :: Python :: 3
Classifier: Programming Language :: Python :: 3.7
Classifier: Programming Language :: Python :: 3.8
Classifier: Programming Language :: Python :: 3.9
Classifier: Programming Language :: Python :: 3.10
Classifier: Programming Language :: Python :: 3.11
Classifier: Programming Language :: Python :: 3.12
Classifier: Operating System :: OS Independent
Requires-Python: >=3.7
License-File: LICENSE
Requires-Dist: numpy>=1.16.0
Requires-Dist: pandas>=1.0.0
Requires-Dist: matplotlib>=3.1.0
Requires-Dist: seaborn>=0.10.0
Requires-Dist: scikit-learn>=0.22.0
Requires-Dist: scipy>=1.4.0
Requires-Dist: colour-science>=0.3.16
Requires-Dist: anndata>=0.5.0
Provides-Extra: full
Requires-Dist: pillow>=8.0.0; extra == "full"
Requires-Dist: ipython>=7.0.0; extra == "full"
Provides-Extra: dev
Requires-Dist: pytest>=6.0.0; extra == "dev"
Requires-Dist: black>=21.0.0; extra == "dev"
Requires-Dist: flake8>=3.8.0; extra == "dev"
Dynamic: license-file
